{
    "configuration": {
        "providers": [
            [
                "local_aer",
                []
            ]
        ],
        "backends": [
            [
                "local_aer",
                "fake_torino"
            ],
            [
                "local_aer",
                "fake_kyiv"
            ],
            [
                "local_aer",
                "fake_sherbrooke"
            ],
            [
                "local_aer",
                "fake_fez"
            ],
            [
                "local_aer",
                "fake_marrakesh"
            ]
        ],
        "execute_flag": false,
        "qasm": "OPENQASM 2.0;\ninclude \"qelib1.inc\";\ngate gate_PauliEvolution(param0) q0,q1,q2,q3,q4,q5,q6,q7,q8,q9 { rzz(1.853613335440787) q0,q1; rzz(1.853613335440787) q0,q6; rzz(1.853613335440787) q1,q3; rzz(1.853613335440787) q2,q6; rzz(1.853613335440787) q2,q8; rzz(1.853613335440787) q3,q4; rzz(1.853613335440787) q4,q8; rzz(1.853613335440787) q5,q7; rzz(1.853613335440787) q5,q9; rzz(1.853613335440787) q7,q9; }\ngate gate_PauliEvolution_130348071899296(param0) q0,q1,q2,q3,q4,q5,q6,q7,q8,q9 { rx(-6.927545672039185) q9; rx(-6.927545672039185) q8; rx(-6.927545672039185) q7; rx(-6.927545672039185) q6; rx(-6.927545672039185) q5; rx(-6.927545672039185) q4; rx(-6.927545672039185) q3; rx(-6.927545672039185) q2; rx(-6.927545672039185) q1; rx(-6.927545672039185) q0; }\ngate gate_PauliEvolution_130348068493200(param0) q0,q1,q2,q3,q4,q5,q6,q7,q8,q9 { rzz(-2.498660255468781) q0,q1; rzz(-2.498660255468781) q0,q6; rzz(-2.498660255468781) q1,q3; rzz(-2.498660255468781) q2,q6; rzz(-2.498660255468781) q2,q8; rzz(-2.498660255468781) q3,q4; rzz(-2.498660255468781) q4,q8; rzz(-2.498660255468781) q5,q7; rzz(-2.498660255468781) q5,q9; rzz(-2.498660255468781) q7,q9; }\ngate gate_PauliEvolution_130348041968848(param0) q0,q1,q2,q3,q4,q5,q6,q7,q8,q9 { rx(1.2889896252192241) q9; rx(1.2889896252192241) q8; rx(1.2889896252192241) q7; rx(1.2889896252192241) q6; rx(1.2889896252192241) q5; rx(1.2889896252192241) q4; rx(1.2889896252192241) q3; rx(1.2889896252192241) q2; rx(1.2889896252192241) q1; rx(1.2889896252192241) q0; }\nqreg q[10];\ncreg meas[10];\nh q[0];\nh q[1];\nh q[2];\nh q[3];\nh q[4];\nh q[5];\nh q[6];\nh q[7];\nh q[8];\nh q[9];\ngate_PauliEvolution(1.853613335440787) q[0],q[1],q[2],q[3],q[4],q[5],q[6],q[7],q[8],q[9];\ngate_PauliEvolution_130348071899296(-3.4637728360195923) q[0],q[1],q[2],q[3],q[4],q[5],q[6],q[7],q[8],q[9];\ngate_PauliEvolution_130348068493200(-2.498660255468781) q[0],q[1],q[2],q[3],q[4],q[5],q[6],q[7],q[8],q[9];\ngate_PauliEvolution_130348041968848(0.6444948126096121) q[0],q[1],q[2],q[3],q[4],q[5],q[6],q[7],q[8],q[9];\nbarrier q[0],q[1],q[2],q[3],q[4],q[5],q[6],q[7],q[8],q[9];\nmeasure q[0] -> meas[0];\nmeasure q[1] -> meas[1];\nmeasure q[2] -> meas[2];\nmeasure q[3] -> meas[3];\nmeasure q[4] -> meas[4];\nmeasure q[5] -> meas[5];\nmeasure q[6] -> meas[6];\nmeasure q[7] -> meas[7];\nmeasure q[8] -> meas[8];\nmeasure q[9] -> meas[9];",
        "results_folder": "./results_nonlinear_vm2",
        "optimizer": "nonlinear",
        "algorithm": "qaoa",
        "size": 10,
        "circuit_name": "qaoa_10",
        "shots": 4096,
        "nonlinear_iterations": 40,
        "nonlinear_annealings": 30
    },
    "model_file": "scenario1.json",
    "circuit_name": "qaoa_10",
    "reasoner_results": {
        "status": "solution_found",
        "dispatch": {
            "local_aer": {
                "fake_torino": [
                    {
                        "shots": 1941
                    }
                ],
                "fake_sherbrooke": [
                    {
                        "shots": 959
                    }
                ],
                "fake_marrakesh": [
                    {
                        "shots": 1196
                    }
                ]
            }
        },
        "score": 575.4028414263018,
        "evaluation": 575.4028414263018,
        "solver_exec_time": 80.18800135236233,
        "total_cost": 490.33568285260355,
        "max_time": 660.4700000000001,
        "min_fidelity": 0.9027
    }
}